sourcemod_api_client/__init__.py
sourcemod_api_client/api_config.py
sourcemod_api_client/models/AdminOut.py
sourcemod_api_client/models/AuthTypeEnum.py
sourcemod_api_client/models/CreateAdminSchema.py
sourcemod_api_client/models/CreateGroupSchema.py
sourcemod_api_client/models/GroupOut.py
sourcemod_api_client/models/GroupOverride_PVT.py
sourcemod_api_client/models/Group_WLC.py
sourcemod_api_client/models/HTTPValidationError.py
sourcemod_api_client/models/Page_AdminOut_.py
sourcemod_api_client/models/Page_GroupOut_.py
sourcemod_api_client/models/UpdateAdminSchema.py
sourcemod_api_client/models/ValidationError.py
sourcemod_api_client/models/__init__.py
sourcemod_api_client/services/__init__.py
sourcemod_api_client/services/admins_groups_service.py
sourcemod_api_client/services/adminss_service.py
sourcemod_api_client/services/async_admins_groups_service.py
sourcemod_api_client/services/async_adminss_service.py
sourcemod_api_client-0.0.1.dist-info/METADATA
sourcemod_api_client-0.0.1.dist-info/WHEEL
sourcemod_api_client-0.0.1.dist-info/RECORD
