Metadata-Version: 2.1
Name: sourcemod-api-client
Version: 0.0.1
Summary: 
Author: Adrian Ciolek
Author-email: ciolek.adrian@protonmail.com
Requires-Python: >=3.11,<4.0
Classifier: Programming Language :: Python :: 3
Classifier: Programming Language :: Python :: 3.11
Classifier: Programming Language :: Python :: 3.12
Requires-Dist: openapi-python-generator (>=0.4.8,<0.5.0)
